Metadata-Version: 1.0
Name: rotlib
Version: 0.91
Summary: Rotation Library
Home-page: http://github.com/soravux/
Author: Yannick Hold-Geoffroy
Author-email: yannickhold@gmail.com
License: UNKNOWN
Platform: UNKNOWN
